{
  "run_timestamp": "2026-06-29T22:04:44.841348+00:00",
  "results": [
    {
      "keyword": "ลิปเปลี่ยนสี",
      "current_score": 0.0,
      "avg_velocity": 10.889,
      "avg_acceleration": 0.0,
      "momentum_score": 7.622,
      "label": "INTRO",
      "source": "live",
      "product_suggestion": {
        "mood_key": "สวย_แต่งหน้า",
        "mood_display": "💄 สวย/แต่งหน้า/ดูแลผิว",
        "products": [
          "เครื่องสำอางราคาจับต้องได้",
          "กระจกแต่งหน้ามีไฟ / อุปกรณ์แต่งหน้า",
          "คอลลาเจน / วิตามินผิว",
          "ครีมกันแดด / เซรั่ม"
        ]
      }
    },
    {
      "keyword": "ครีมกันแดดโกลว์",
      "current_score": 0.0,
      "avg_velocity": 0.0,
      "avg_acceleration": 0.0,
      "momentum_score": 0.0,
      "label": "STABLE",
      "source": "live",
      "product_suggestion": {
        "mood_key": "สวย_แต่งหน้า",
        "mood_display": "💄 สวย/แต่งหน้า/ดูแลผิว",
        "products": [
          "เครื่องสำอางราคาจับต้องได้",
          "กระจกแต่งหน้ามีไฟ / อุปกรณ์แต่งหน้า",
          "คอลลาเจน / วิตามินผิว",
          "ครีมกันแดด / เซรั่ม"
        ]
      }
    },
    {
      "keyword": "เซรั่มหน้าใส",
      "current_score": 0.0,
      "avg_velocity": 0.0,
      "avg_acceleration": 0.0,
      "momentum_score": 0.0,
      "label": "STABLE",
      "source": "live",
      "product_suggestion": {
        "mood_key": "สวย_แต่งหน้า",
        "mood_display": "💄 สวย/แต่งหน้า/ดูแลผิว",
        "products": [
          "เครื่องสำอางราคาจับต้องได้",
          "กระจกแต่งหน้ามีไฟ / อุปกรณ์แต่งหน้า",
          "คอลลาเจน / วิตามินผิว",
          "ครีมกันแดด / เซรั่ม"
        ]
      }
    },
    {
      "keyword": "น้ำหอมติดทน",
      "current_score": 0.0,
      "avg_velocity": 0.0,
      "avg_acceleration": 0.0,
      "momentum_score": 0.0,
      "label": "STABLE",
      "source": "live",
      "product_suggestion": {
        "mood_key": "สวย_แต่งหน้า",
        "mood_display": "💄 สวย/แต่งหน้า/ดูแลผิว",
        "products": [
          "เครื่องสำอางราคาจับต้องได้",
          "กระจกแต่งหน้ามีไฟ / อุปกรณ์แต่งหน้า",
          "คอลลาเจน / วิตามินผิว",
          "ครีมกันแดด / เซรั่ม"
        ]
      }
    },
    {
      "keyword": "คอนซีลเลอร์",
      "current_score": 0.0,
      "avg_velocity": -7.333,
      "avg_acceleration": 0.0,
      "momentum_score": -5.133,
      "label": "DECLINE",
      "source": "live",
      "product_suggestion": {
        "mood_key": "สวย_แต่งหน้า",
        "mood_display": "💄 สวย/แต่งหน้า/ดูแลผิว",
        "products": [
          "เครื่องสำอางราคาจับต้องได้",
          "กระจกแต่งหน้ามีไฟ / อุปกรณ์แต่งหน้า",
          "คอลลาเจน / วิตามินผิว",
          "ครีมกันแดด / เซรั่ม"
        ]
      }
    },
    {
      "keyword": "คอลลาเจน",
      "current_score": 0.0,
      "avg_velocity": 0.333,
      "avg_acceleration": 4.667,
      "momentum_score": 1.633,
      "label": "INTRO",
      "source": "live",
      "product_suggestion": {
        "mood_key": "สวย_แต่งหน้า",
        "mood_display": "💄 สวย/แต่งหน้า/ดูแลผิว",
        "products": [
          "เครื่องสำอางราคาจับต้องได้",
          "กระจกแต่งหน้ามีไฟ / อุปกรณ์แต่งหน้า",
          "คอลลาเจน / วิตามินผิว",
          "ครีมกันแดด / เซรั่ม"
        ]
      }
    },
    {
      "keyword": "โพรไบโอติก",
      "current_score": 0.0,
      "avg_velocity": 0.0,
      "avg_acceleration": 2.0,
      "momentum_score": 0.6,
      "label": "STABLE",
      "source": "live",
      "product_suggestion": {
        "mood_key": "default",
        "mood_display": "❓ เดาอารมณ์ไม่ออก",
        "products": [
          "เลือกสินค้าที่กำลังไวรัลใน TikTok Shop (#TikTokMadeMeBuyIt)",
          "ดูว่าคีย์เวิร์ดนี้คนค้นเพราะอะไร แล้วจับคู่สินค้าแก้ปัญหานั้น"
        ]
      }
    },
    {
      "keyword": "วิตามินผิว",
      "current_score": 0.0,
      "avg_velocity": 0.0,
      "avg_acceleration": 0.0,
      "momentum_score": 0.0,
      "label": "STABLE",
      "source": "live",
      "product_suggestion": {
        "mood_key": "สวย_แต่งหน้า",
        "mood_display": "💄 สวย/แต่งหน้า/ดูแลผิว",
        "products": [
          "เครื่องสำอางราคาจับต้องได้",
          "กระจกแต่งหน้ามีไฟ / อุปกรณ์แต่งหน้า",
          "คอลลาเจน / วิตามินผิว",
          "ครีมกันแดด / เซรั่ม"
        ]
      }
    },
    {
      "keyword": "ขนมเกาหลี",
      "current_score": 0.0,
      "avg_velocity": 0.0,
      "avg_acceleration": 0.0,
      "momentum_score": 0.0,
      "label": "STABLE",
      "source": "live",
      "product_suggestion": {
        "mood_key": "กิน_อาหาร",
        "mood_display": "🍜 กิน/รีวิวอาหาร",
        "products": [
          "ขนม/ของกินไวรัล (เกาหลี/ญี่ปุ่น)",
          "เครื่องปรุง/น้ำจิ้มสำเร็จรูป",
          "อุปกรณ์ทำอาหาร/เครื่องครัว",
          "อาหารเสริม/เครื่องดื่มสุขภาพ"
        ]
      }
    },
    {
      "keyword": "กาแฟลดน้ำหนัก",
      "current_score": 0.0,
      "avg_velocity": 0.0,
      "avg_acceleration": 0.0,
      "momentum_score": 0.0,
      "label": "STABLE",
      "source": "live",
      "product_suggestion": {
        "mood_key": "กิน_อาหาร",
        "mood_display": "🍜 กิน/รีวิวอาหาร",
        "products": [
          "ขนม/ของกินไวรัล (เกาหลี/ญี่ปุ่น)",
          "เครื่องปรุง/น้ำจิ้มสำเร็จรูป",
          "อุปกรณ์ทำอาหาร/เครื่องครัว",
          "อาหารเสริม/เครื่องดื่มสุขภาพ"
        ]
      }
    },
    {
      "keyword": "เครื่องฟอกอากาศ",
      "current_score": 0.0,
      "avg_velocity": 0.0,
      "avg_acceleration": 2.222,
      "momentum_score": 0.667,
      "label": "STABLE",
      "source": "live",
      "product_suggestion": {
        "mood_key": "default",
        "mood_display": "❓ เดาอารมณ์ไม่ออก",
        "products": [
          "เลือกสินค้าที่กำลังไวรัลใน TikTok Shop (#TikTokMadeMeBuyIt)",
          "ดูว่าคีย์เวิร์ดนี้คนค้นเพราะอะไร แล้วจับคู่สินค้าแก้ปัญหานั้น"
        ]
      }
    },
    {
      "keyword": "ที่ดูดฝุ่นไร้สาย",
      "current_score": 0.0,
      "avg_velocity": 0.0,
      "avg_acceleration": 0.0,
      "momentum_score": 0.0,
      "label": "STABLE",
      "source": "live",
      "product_suggestion": {
        "mood_key": "ไลฟ์สไตล์_ทำความสะอาด",
        "mood_display": "🧹 ไลฟ์สไตล์/จัดบ้าน/ทำความสะอาด",
        "products": [
          "น้ำยาขจัดคราบ / อุปกรณ์ทำความสะอาด",
          "อุปกรณ์จัดระเบียบโต๊ะ/ห้อง",
          "เครื่องใช้ไฟฟ้าในครัว (หม้อทอด/เครื่องดูดฝุ่น)",
          "กล่องเก็บของ / ชั้นวาง"
        ]
      }
    },
    {
      "keyword": "หม้อทอดไร้น้ำมัน",
      "current_score": 0.0,
      "avg_velocity": 0.0,
      "avg_acceleration": 0.0,
      "momentum_score": 0.0,
      "label": "STABLE",
      "source": "live",
      "product_suggestion": {
        "mood_key": "ไลฟ์สไตล์_ทำความสะอาด",
        "mood_display": "🧹 ไลฟ์สไตล์/จัดบ้าน/ทำความสะอาด",
        "products": [
          "น้ำยาขจัดคราบ / อุปกรณ์ทำความสะอาด",
          "อุปกรณ์จัดระเบียบโต๊ะ/ห้อง",
          "เครื่องใช้ไฟฟ้าในครัว (หม้อทอด/เครื่องดูดฝุ่น)",
          "กล่องเก็บของ / ชั้นวาง"
        ]
      }
    },
    {
      "keyword": "ไฟ LED ติดผนัง",
      "current_score": 0.0,
      "avg_velocity": 0.0,
      "avg_acceleration": 0.0,
      "momentum_score": 0.0,
      "label": "STABLE",
      "source": "live",
      "product_suggestion": {
        "mood_key": "default",
        "mood_display": "❓ เดาอารมณ์ไม่ออก",
        "products": [
          "เลือกสินค้าที่กำลังไวรัลใน TikTok Shop (#TikTokMadeMeBuyIt)",
          "ดูว่าคีย์เวิร์ดนี้คนค้นเพราะอะไร แล้วจับคู่สินค้าแก้ปัญหานั้น"
        ]
      }
    },
    {
      "keyword": "เครื่องชงกาแฟ",
      "current_score": 0.0,
      "avg_velocity": 0.0,
      "avg_acceleration": 0.0,
      "momentum_score": 0.0,
      "label": "STABLE",
      "source": "live",
      "product_suggestion": {
        "mood_key": "กิน_อาหาร",
        "mood_display": "🍜 กิน/รีวิวอาหาร",
        "products": [
          "ขนม/ของกินไวรัล (เกาหลี/ญี่ปุ่น)",
          "เครื่องปรุง/น้ำจิ้มสำเร็จรูป",
          "อุปกรณ์ทำอาหาร/เครื่องครัว",
          "อาหารเสริม/เครื่องดื่มสุขภาพ"
        ]
      }
    },
    {
      "keyword": "เสื้อโอเวอร์ไซส์",
      "current_score": 0.0,
      "avg_velocity": 0.0,
      "avg_acceleration": 0.0,
      "momentum_score": 0.0,
      "label": "STABLE",
      "source": "live",
      "product_suggestion": {
        "mood_key": "แฟชั่น_แต่งตัว",
        "mood_display": "👗 แฟชั่น/แต่งตัว/OOTD",
        "products": [
          "เสื้อผ้าแฟชั่นตามเทรนด์",
          "กระเป๋า / รองเท้า",
          "เครื่องประดับ / แอคเซสเซอรี่",
          "อุปกรณ์รีดผ้า / ที่เก็บเสื้อผ้า"
        ]
      }
    },
    {
      "keyword": "กางเกงขายาวทรงสวย",
      "current_score": 0.0,
      "avg_velocity": 0.0,
      "avg_acceleration": 0.0,
      "momentum_score": 0.0,
      "label": "STABLE",
      "source": "live",
      "product_suggestion": {
        "mood_key": "สวย_แต่งหน้า",
        "mood_display": "💄 สวย/แต่งหน้า/ดูแลผิว",
        "products": [
          "เครื่องสำอางราคาจับต้องได้",
          "กระจกแต่งหน้ามีไฟ / อุปกรณ์แต่งหน้า",
          "คอลลาเจน / วิตามินผิว",
          "ครีมกันแดด / เซรั่ม"
        ]
      }
    },
    {
      "keyword": "เดรสออกงาน",
      "current_score": 0.0,
      "avg_velocity": 0.0,
      "avg_acceleration": 0.0,
      "momentum_score": 0.0,
      "label": "STABLE",
      "source": "live",
      "product_suggestion": {
        "mood_key": "ตลก_เครียดงาน",
        "mood_display": "😩 ตลก/เครียดเรื่องงาน",
        "products": [
          "อาหารเสริมแก้ปวดหัว / วิตามินบำรุงสมอง",
          "หมอนรองคอ / หมอนรองหลังออฟฟิศ",
          "ขนมขบเคี้ยวแปลกๆ / กาแฟ",
          "ยาหม่อง / แผ่นแปะคลายกล้ามเนื้อ"
        ]
      }
    },
    {
      "keyword": "กระเป๋าสะพาย",
      "current_score": 0.0,
      "avg_velocity": -2.111,
      "avg_acceleration": 3.111,
      "momentum_score": -0.544,
      "label": "DECLINE",
      "source": "live",
      "product_suggestion": {
        "mood_key": "แฟชั่น_แต่งตัว",
        "mood_display": "👗 แฟชั่น/แต่งตัว/OOTD",
        "products": [
          "เสื้อผ้าแฟชั่นตามเทรนด์",
          "กระเป๋า / รองเท้า",
          "เครื่องประดับ / แอคเซสเซอรี่",
          "อุปกรณ์รีดผ้า / ที่เก็บเสื้อผ้า"
        ]
      }
    },
    {
      "keyword": "รองเท้าผ้าใบ",
      "current_score": 0.0,
      "avg_velocity": -2.778,
      "avg_acceleration": 2.0,
      "momentum_score": -1.344,
      "label": "DECLINE",
      "source": "live",
      "product_suggestion": {
        "mood_key": "แฟชั่น_แต่งตัว",
        "mood_display": "👗 แฟชั่น/แต่งตัว/OOTD",
        "products": [
          "เสื้อผ้าแฟชั่นตามเทรนด์",
          "กระเป๋า / รองเท้า",
          "เครื่องประดับ / แอคเซสเซอรี่",
          "อุปกรณ์รีดผ้า / ที่เก็บเสื้อผ้า"
        ]
      }
    }
  ]
}